{
    "msg": "ok",
    "status": 0,
    "data": {
        "detailMovie": {
            "albumIng": "http://p1.meituan.net/w.h/movie/967b253953bc7e660cfadbf9d78f67b62852693.jpg",
            "bingWatch": 128925,
            "bingWatchst": 0,
            "cat": "动作，惊悚，冒险",
            "comScorePerson": true,
            "commented": false,
            "dir": "柯汶利",
            "dra": "曾凭借《贫民窟的百万富翁》捧得奥斯卡最佳导演奖的丹尼·鲍尔已基本被锁定为《邦德25》导演，离最后敲定只有一步之遥，只要与之长期合作的John Hodge执笔的剧本通过验收。据《每日邮报》拥有007电影独家消息源的Baz Bamigboye推特透露，007系列电影的制片人芭芭拉·布洛柯里和迈克尔·G·威尔逊很“愿意”达成这项合作。 消息源表示”他们告诉了芭芭拉一些想法，那是她从没想过的，但是她为那些想法感到兴奋——而她的合作伙伴迈克尔也一样。但是最重要的推动者还是丹尼尔，他支持丹尼来执导，他爱上了那些完全不同的东西，“并且“每个人似乎都支持这一切发生。",
            "dur": 102,
            "egg": true,
            "enm": "No Time to Die",
            "episodeDur": 0,
            "episodes": 0,
            "fra": "英国",
            "frt": "2020-11-25美国上映",
            "globaReleased": true,
            "id": 345808,
            "img": "https://p0.meituan.net/movie/6236e2d60e3a4afd283d75f1778390999228257.jpg@464w_644h_1e_1c" ,
            "latestEpisode": 0,
            "modcsSt": false,
            "movieType": 0,
            "multiPub": true,
            "musicNum": 1,
            "musicStar": "肖央",
            "nm": "007",
            "onSale": false,
            "onlinePlay": false,
            "orderSt": 0,
            "oriLang": "中文",
            "photos": [
                "https://p0.meituan.net/movie/adbb1e5ec7d623600cb45ae8c8a95fec9649228.jpg@106w_106h_1e_1c",
                "https://p0.meituan.net/movie/47d4d6e4df15d8040f7d786051f5750b10236902.jpg@106w_106h_1e_1c",
                "https://p1.meituan.net/movie/8b7045118c027615282400d8d1d87eac10799336.jpg@106w_106h_1e_1c",
                "https://p0.meituan.net/movie/e4430421ec97f841744b85a849d1e49e10599588.jpg@106w_106h_1e_1c",
                "https://p0.meituan.net/movie/dc6310d6f5444d0d61c2ca3b32c716168839917.jpg@106w_106h_1e_1c",
                "https://p1.meituan.net/movie/e7083b6d1437887113d08d206ea1c73b89975.jpg@106w_106h_1e_1c",
                "https://p0.meituan.net/movie/aa2ded64bbac1807850ac86e5810ba47248320.jpg@106w_106h_1e_1c",
                "https://p0.meituan.net/movie/0665324f4b14028e897b542812d322b3220345.jpg@106w_106h_1e_1c"
            ],
            "pn": 272,
            "preScorePersona": false,
            "proScore": 0,
            "proScoreNum": 1,
            "pubDesc": "2019-01-25大陆上映",
            "rt": "2019-12-13",
            "sc": 0,
            "scm": "http://p1.meituan.net/w.h/movie/967b253953bc7e660cfadbf9d78f67b62852693.jpg",
            "scoreLabel": "猫眼票评分",
            "showst": 0,
            "snum": 165552,
            "src": "中国",
            "star": "肖央，陈述",
            "type": 0,
            "vd": "",
            "ver": "2D/IMAX 2D/中国巨幕",
            "videoIng": "http://p1.meituan.net/w.h/movie/967b253953bc7e660cfadbf9d78f67b62852693.jpg"
        }
       
    }
}